to_sequential/__init__.py
to_sequential/main.py
to_sequential-0.2.0.dist-info/METADATA
to_sequential-0.2.0.dist-info/WHEEL
to_sequential-0.2.0.dist-info/top_level.txt
to_sequential-0.2.0.dist-info/RECORD
