Metadata-Version: 2.1
Name: to_sequential
Version: 0.2.0
Summary: A utility to generate sequential data for sequential models from a Pandas DataFrame.
Home-page: https://github.com/bhyeanhasan/to-sequential
Author: Md. Babul Hasan (Noyon)
Author-email: bhyean@gmail.com
Classifier: Programming Language :: Python :: 3
Classifier: License :: OSI Approved :: MIT License
Classifier: Operating System :: OS Independent
Requires-Python: >=3.6
Requires-Dist: pandas >=1.0.0
Requires-Dist: numpy >=1.18.0
